pandleau/__init__.py
pandleau/pandleau.py
pandleau-0.4.1.dist-info/LICENSE
pandleau-0.4.1.dist-info/METADATA
pandleau-0.4.1.dist-info/WHEEL
pandleau-0.4.1.dist-info/top_level.txt
pandleau-0.4.1.dist-info/RECORD
