Metadata-Version: 2.1
Name: pandleau
Version: 0.4.1
Summary: A quick and easy way to convert a Pandas DataFrame to a Tableau extract.
Home-page: https://github.com/bwiley1/pandleau
Author: Benjamin Wiley, Zhirui(Jerry) Wang, Aaron Wiegel, Pointy Shiny Burning, Harrison
Author-email: bewi7122@colorado.edu, zw2389@columbia.edu, aawiegel@gmail.com
License: MIT
Download-URL: https://github.com/bwiley1/pandleau/dist/pandleau-0.4.1.tar.gz
Keywords: tableau pandas extract tde hyper
Platform: UNKNOWN
Classifier: Programming Language :: Python
Requires-Dist: pandas
Requires-Dist: numpy
Requires-Dist: tqdm
